antiocr/__init__.py
antiocr/__version__.py
antiocr/anti_ocr.py
antiocr/app.py
antiocr/bg_generator.py
antiocr/consts.py
antiocr/renderer.py
antiocr/utils.py
antiocr/resources/bg.jpeg
antiocr-0.1.data/data/bg.jpeg
antiocr-0.1.dist-info/LICENSE
antiocr-0.1.dist-info/METADATA
antiocr-0.1.dist-info/WHEEL
antiocr-0.1.dist-info/entry_points.txt
antiocr-0.1.dist-info/top_level.txt
antiocr-0.1.dist-info/RECORD
