Metadata-Version: 2.1
Name: antiocr
Version: 0.1
Summary: Python3 package for generating text images which can't be recognized by AI
Home-page: https://github.com/breezedeus/antiocr
Author: breezedeus
Author-email: breezedeus@163.com
License: Apache 2.0
Platform: Mac
Platform: Linux
Platform: Windows
Classifier: Development Status :: 4 - Beta
Classifier: Operating System :: OS Independent
Classifier: Intended Audience :: Developers
Classifier: License :: OSI Approved :: Apache Software License
Classifier: Programming Language :: Python
Classifier: Programming Language :: Python :: Implementation
Classifier: Programming Language :: Python :: 3
Classifier: Programming Language :: Python :: 3.6
Classifier: Programming Language :: Python :: 3.7
Classifier: Programming Language :: Python :: 3.8
Classifier: Topic :: Scientific/Engineering :: Artificial Intelligence
Requires-Dist: click
Requires-Dist: tqdm
Requires-Dist: pillow (>=5.3.0)
Requires-Dist: pypinyin
Provides-Extra: dev
Requires-Dist: pip-tools ; extra == 'dev'
Requires-Dist: pytest ; extra == 'dev'
